setup.py
five91/__init__.py
five91/five91.py
five91.egg-info/PKG-INFO
five91.egg-info/SOURCES.txt
five91.egg-info/dependency_links.txt
five91.egg-info/not-zip-safe
five91.egg-info/requires.txt
five91.egg-info/top_level.txt