Metadata-Version: 1.0
Name: five91
Version: 0.1
Summary: Simple 591.com.tw wrapper
Home-page: http://github.com/tzengyuxio/python-five91
Author: Tzeng Yuxio
Author-email: tzengyuxio@gmail.com
License: MIT
Platform: UNKNOWN
